py_linq_sql/__init__.py
py_linq_sql/build_request/__init__.py
py_linq_sql/build_request/alter.py
py_linq_sql/build_request/build.py
py_linq_sql/build_request/consult.py
py_linq_sql/build_request/consult_aggregate.py
py_linq_sql/build_request/consult_context.py
py_linq_sql/build_request/consult_terminal.py
py_linq_sql/build_request/one.py
py_linq_sql/config/__init__.py
py_linq_sql/config/config.py
py_linq_sql/exception/__init__.py
py_linq_sql/exception/exception.py
py_linq_sql/py.typed
py_linq_sql/sql_enumerable/__init__.py
py_linq_sql/sql_enumerable/sql_enumerable.py
py_linq_sql/utils/__init__.py
py_linq_sql/utils/classes/__init__.py
py_linq_sql/utils/classes/enum.py
py_linq_sql/utils/classes/magicdotpath.py
py_linq_sql/utils/classes/op_and_func_of_mdp.py
py_linq_sql/utils/classes/other_classes.py
py_linq_sql/utils/db.py
py_linq_sql/utils/execute.py
py_linq_sql/utils/functions/__init__.py
py_linq_sql/utils/functions/aggregate_functions.py
py_linq_sql/utils/functions/join_functions.py
py_linq_sql/utils/functions/magic_dp_hyperb_functions.py
py_linq_sql/utils/functions/magic_dp_maths_functions.py
py_linq_sql/utils/functions/magic_dp_other_functions.py
py_linq_sql/utils/functions/magic_dp_str_functions.py
py_linq_sql/utils/functions/magic_dp_trigo_functions.py
py_linq_sql/utils/functions/other_functions.py
py_linq_sql/utils/functions/path_functions.py
py_linq_sql/utils/functions/predicate_functions.py
py_linq_sql-1.11.0.1.dist-info/LICENSE.md
py_linq_sql-1.11.0.1.dist-info/METADATA
py_linq_sql-1.11.0.1.dist-info/WHEEL
py_linq_sql-1.11.0.1.dist-info/RECORD
