Metadata-Version: 2.1
Name: py-linq-sql
Version: 1.11.0.1
Summary: A Python module used for interacting with sql database using LINQ syntax.
Home-page: https://gitlab.obspm.fr/exoplanet/py-linq-sql
License: EUPL v1.2
Keywords: linq,py-linq,sql,database,requests
Author: CHOSSON Ulysse
Author-email: ulysse.chosson@obspm.fr
Maintainer: CHOSSON Ulysse
Maintainer-email: ulysse.chosson@obspm.fr
Requires-Python: >=3.10,<4.0.0
Classifier: License :: Other/Proprietary License
Classifier: Programming Language :: Python :: 3
Classifier: Programming Language :: Python :: 3.10
Classifier: Programming Language :: Python :: 3.11
Classifier: Programming Language :: Python :: 3.12
Requires-Dist: dotmap (>=1.3.30,<2.0.0)
Requires-Dist: psycopg (>=3.1.4,<4.0.0)
Requires-Dist: py-linq (==1.3.0)
Requires-Dist: pyyaml (>=6.0,<7.0)
Requires-Dist: rich (>=12.6.0)
Requires-Dist: six (>=1.16.0,<2.0.0)
Requires-Dist: strenum (>=0.4.8,<0.5.0)
Requires-Dist: toml (>=0.10.2,<0.11.0)
Requires-Dist: types-pyyaml (>=6.0.12.1,<7.0.0.0)
Requires-Dist: types-toml (>=0.10.8,<0.11.0)
Project-URL: Documentation, https://py-linq-sql.readthedocs.io/en/latest/
Project-URL: Repository, https://gitlab.obspm.fr/exoplanet/py-linq-sql
